{
    "a": {
        "teacher_email": 0
    },
    "b": {
        "teacher_email": 1
    },
    "c": {
        "teacher_email": 2
    },
    "d": {
        "teacher_email": 3
    },
    "e": {
        "teacher_email": 4
    },
    "f": {
        "teacher_email": 5
    },
    "g": {
        "teacher_email": 6
    },
    "h": {
        "teacher_email": 7
    },
    "i": {
        "teacher_email": 8
    },
    "j": {
        "teacher_email": 9
    },
    "k": {
        "teacher_email": 10
    },
    "l": {
        "teacher_email": 11
    },
    "m": {
        "teacher_email": 12
    },
    "n": {
        "teacher_email": 13
    },
    "o": {
        "teacher_email": 14
    },
    "p": {
        "teacher_email": 15
    },
    "q": {
        "teacher_email": 16
    },
    "r": {
        "teacher_email": 17
    },
    "s": {
        "teacher_email": 18
    },
    "t": {
        "teacher_email": 19
    },
    "u": {
        "teacher_email": 20
    },
    "v": {
        "teacher_email": 21
    },
    "w": {
        "teacher_email": 22
    },
    "x": {
        "teacher_email": 23
    },
    "y": {
        "teacher_email": 24
    },
    "z": {
        "teacher_email": 25
    }
}
